.gitignore
setup.py
repair_seq/__init__.py
repair_seq/arrayed_experiment_group.py
repair_seq/base_editor.py
repair_seq/beta_binomial.py
repair_seq/bootstrapper.py
repair_seq/build_guide_specific_targets.py
repair_seq/cluster.py
repair_seq/coherence.py
repair_seq/collapse.py
repair_seq/collapse_cython.pyx
repair_seq/common_sequences.py
repair_seq/convert_outcomes.py
repair_seq/demux.py
repair_seq/demux_arrayed_experiments.py
repair_seq/demux_for_SRA.py
repair_seq/demux_gDNA.py
repair_seq/experiment_group.py
repair_seq/guide_library.py
repair_seq/paired_end_experiment.py
repair_seq/perturb_seq.py
repair_seq/pooled_layout.py
repair_seq/pooled_screen.py
repair_seq/prime_editing_experiment.py
repair_seq/prime_editing_layout.py
repair_seq/quantiles.py
repair_seq/repair-seq
repair_seq/replicates.py
repair_seq/single_end_experiment.py
repair_seq/statistics.py
repair_seq/twin_prime_layout.py
repair_seq.egg-info/PKG-INFO
repair_seq.egg-info/SOURCES.txt
repair_seq.egg-info/dependency_links.txt
repair_seq.egg-info/requires.txt
repair_seq.egg-info/top_level.txt
repair_seq/test/.gitignore
repair_seq/test/build_read_sets.py
repair_seq/test/index_locations.yaml
repair_seq/test/test_pegRNAs.py
repair_seq/test/test_read_sets.py
repair_seq/test/read_sets/PE2_screen/alignments.bam
repair_seq/test/read_sets/PE2_screen/expected_values.yaml
repair_seq/test/read_sets/PE3+50_screen/alignments.bam
repair_seq/test/read_sets/PE3+50_screen/expected_values.yaml
repair_seq/test/read_sets/PE3-50_screen/alignments.bam
repair_seq/test/read_sets/PE3-50_screen/expected_values.yaml
repair_seq/test/read_sets/twin_prime_fig_1C_attB_A30_B30_1/alignments.bam
repair_seq/test/read_sets/twin_prime_fig_1C_attB_A30_B30_1/expected_values.yaml
repair_seq/test/read_sets/twin_prime_fig_2C_PAH_E4_24bp_overlap_epegRNA_1/alignments.bam
repair_seq/test/read_sets/twin_prime_fig_2C_PAH_E4_24bp_overlap_epegRNA_1/expected_values.yaml
repair_seq/test/read_sets/twin_prime_fig_2C_PAH_E7a_22bp_overlap_epegRNA_1/alignments.bam
repair_seq/test/read_sets/twin_prime_fig_2C_PAH_E7a_22bp_overlap_epegRNA_1/expected_values.yaml
