Metadata-Version: 2.1
Name: repair-seq
Version: 1.0.3
Summary: processing, analysis, and visualization of data from Repair-seq screens
Home-page: https://github.com/jeffhussmann/repair-seq
Author: Jeff Hussmann
Author-email: jeff.hussmann@gmail.com
License: UNKNOWN
Platform: UNKNOWN
Requires-Python: >=3.7
